[
    {
      "type": "PAGE",
      "title": "Dashboard"
    },
    {
      "type": "PARENT",
      "title": "Compute and Storage",
      "nav": [
        {
          "type": "PAGE",
          "title": "VMs",
          "sections": ["Summary (v1+)", "List#", "Templates", null, "Alerts", "Events", "Metrics"]
        },
        {
          "type": "PAGE",
          "title": "Images",
          "sections": ["Private Images#", "Public Catalog Images"]
        },
        {
          "type": "PAGE",
          "title": "Volumes (v1+)",
          "sections": ["List#", " ", "Metrics"]
        },
        {
          "type": "PAGE",
          "title": "Dedicated Domains",
          "sections": ["List#", " ", "Metrics (v1+)"]
        }
      ]
    },
    {
        "type": "PARENT",
        "title": "Networking and Security",
        "nav": [
          {
            "type": "PAGE",
            "title": "Virtual Private Cloud",
            "sections": ["Summary", "List#", "", "VPN", "Direct Connect"]
          },
          {
            "type": "PAGE",
            "title": "Load Balancers (v1+)",
            "sections": ["List#", " ", "Metrics (v1+)"]
          },
          {
            "type": "PAGE",
            "title": "Security (v1+)",
            "sections": ["Summary", "Security Policies#", "Security Plannin", "", "Traffic Redirection"]
          }
        ]
      },
    {
      "type": "SEPARATOR"
    },
    {
      "type": "PAGE",
      "title": "Data Protection",
      "sections": ["Protection Plans#", "Recovery Plans", "Recoverable Entities"]
    },
    {
      "type": "SEPARATOR"
    },
    {
      "type": "PARENT",
      "title": "Administration",
      "nav": [
        {
          "type": "PAGE",
          "title": "Categories",
          "sections": ["List#"]
        },
        {
          "type": "PAGE",
          "title": "Availability Zones",
          "sections": ["List#"]
        }
      ]
    },
    {
      "type": "SEPARATOR"
    }
  ]